logger_lib/__init__.py
logger_lib/core.py
dscss-1.0.1.dist-info/METADATA
dscss-1.0.1.dist-info/WHEEL
dscss-1.0.1.dist-info/top_level.txt
dscss-1.0.1.dist-info/RECORD
